mlflow/__init__.py
mlflow/__main__.py
mlflow/client.py
mlflow/db.py
mlflow/environment_variables.py
mlflow/exceptions.py
mlflow/experiments.py
mlflow/mismatch.py
mlflow/ml_package_versions.py
mlflow/py.typed
mlflow/runs.py
mlflow/version.py
mlflow/agno/__init__.py
mlflow/agno/autolog_v1.py
mlflow/agno/autolog_v2.py
mlflow/agno/utils.py
mlflow/anthropic/__init__.py
mlflow/anthropic/autolog.py
mlflow/anthropic/chat.py
mlflow/autogen/__init__.py
mlflow/autogen/chat.py
mlflow/azure/__init__.py
mlflow/azure/client.py
mlflow/bedrock/__init__.py
mlflow/bedrock/_autolog.py
mlflow/bedrock/chat.py
mlflow/bedrock/stream.py
mlflow/bedrock/utils.py
mlflow/crewai/__init__.py
mlflow/crewai/autolog.py
mlflow/dspy/__init__.py
mlflow/dspy/autolog.py
mlflow/dspy/callback.py
mlflow/dspy/constant.py
mlflow/dspy/load.py
mlflow/dspy/save.py
mlflow/dspy/util.py
mlflow/dspy/wrapper.py
mlflow/entities/__init__.py
mlflow/entities/_job.py
mlflow/entities/_job_status.py
mlflow/entities/_mlflow_object.py
mlflow/entities/assessment.py
mlflow/entities/assessment_error.py
mlflow/entities/assessment_source.py
mlflow/entities/dataset.py
mlflow/entities/dataset_input.py
mlflow/entities/dataset_record.py
mlflow/entities/dataset_record_source.py
mlflow/entities/dataset_summary.py
mlflow/entities/document.py
mlflow/entities/entity_type.py
mlflow/entities/evaluation_dataset.py
mlflow/entities/experiment.py
mlflow/entities/experiment_tag.py
mlflow/entities/file_info.py
mlflow/entities/gateway_endpoint.py
mlflow/entities/gateway_secrets.py
mlflow/entities/input_tag.py
mlflow/entities/lifecycle_stage.py
mlflow/entities/logged_model.py
mlflow/entities/logged_model_input.py
mlflow/entities/logged_model_output.py
mlflow/entities/logged_model_parameter.py
mlflow/entities/logged_model_status.py
mlflow/entities/logged_model_tag.py
mlflow/entities/metric.py
mlflow/entities/multipart_upload.py
mlflow/entities/param.py
mlflow/entities/run.py
mlflow/entities/run_data.py
mlflow/entities/run_info.py
mlflow_tracing-3.8.0.dist-info/licenses/LICENSE.txt
mlflow_tracing-3.8.0.dist-info/METADATA
mlflow_tracing-3.8.0.dist-info/WHEEL
mlflow_tracing-3.8.0.dist-info/top_level.txt
mlflow_tracing-3.8.0.dist-info/RECORD
