Metadata-Version: 2.4
Name: mlflow-tracing
Version: 3.8.0
Summary: MLflow Tracing SDK is an open-source, lightweight Python package that only includes the minimum set of dependencies and functionality to instrument your code/models/agents with MLflow Tracing.
Maintainer-email: Databricks <mlflow-oss-maintainers@googlegroups.com>
License: Copyright 2018 Databricks, Inc.  All rights reserved.
Project-URL: homepage, https://mlflow.org
Project-URL: issues, https://github.com/mlflow/mlflow/issues
Project-URL: documentation, https://mlflow.org/docs/latest
Project-URL: repository, https://github.com/mlflow/mlflow
Keywords: mlflow,ai,databricks
Classifier: Development Status :: 5 - Production/Stable
Classifier: Intended Audience :: Developers
Classifier: Intended Audience :: End Users/Desktop
Classifier: Intended Audience :: Science/Research
Classifier: Intended Audience :: Information Technology
Classifier: Topic :: Scientific/Engineering :: Artificial Intelligence
Classifier: Topic :: Software Development :: Libraries :: Python Modules
Classifier: License :: OSI Approved :: Apache Software License
Classifier: Operating System :: OS Independent
Classifier: Programming Language :: Python :: 3.10
Requires-Python: >=3.10
License-File: LICENSE.txt
Requires-Dist: cachetools<7,>=5.0.0
Requires-Dist: databricks-sdk<1,>=0.20.0
Requires-Dist: opentelemetry-api<3,>=1.9.0
Requires-Dist: opentelemetry-proto<3,>=1.9.0
Requires-Dist: opentelemetry-sdk<3,>=1.9.0
Requires-Dist: packaging<26
Requires-Dist: protobuf<7,>=3.12.0
Requires-Dist: pydantic<3,>=2.0.0
Dynamic: license-file
